{
    "output_dir": "agglomerative-new",
    "dataset": "drone",
    "embedding": "sbert",
    "threshold": 0.26,
    "save_model": false,
    "started_at": "2024-08-22 03:08:40.450371",
    "ended_at": "2024-08-22 03:08:40.458658",
    "duration": "8.287 miliseconds",
    "eval_score": {
        "group_accuracy": "0.51884",
        "singleton_f1": "0.74492",
        "ami_score": "0.74766",
        "nmi_score": "0.96239",
        "ari_score": "0.75673",
        "hgi_score": "0.96345",
        "cpi_score": "0.96133",
        "vmi_score": "0.96239",
        "fmi_score": "0.75835",
        "silhouette_avg": "0.2145",
        "calinski_harabasz_avg": "8.47695"
    }
}