{
    "output_dir": "birch-new",
    "dataset": "OpenSSH",
    "embedding": "drone-sbert",
    "threshold": 0.12,
    "save_model": false,
    "started_at": "2024-08-18 07:23:54.607134",
    "ended_at": "2024-08-18 07:23:54.759704",
    "duration": "152.57 miliseconds",
    "eval_score": {
        "group_accuracy": "0.102",
        "singleton_f1": "0.096",
        "ami_score": "0.7275",
        "nmi_score": "0.76634",
        "ari_score": "0.71402",
        "hgi_score": "0.93726",
        "cpi_score": "0.64815",
        "vmi_score": "0.76634",
        "fmi_score": "0.75246",
        "silhouette_avg": "0.64132",
        "calinski_harabasz_avg": "557.7896"
    }
}