{
    "output_dir": "birch-new",
    "dataset": "Windows",
    "embedding": "instructor-large",
    "threshold": 0.06,
    "save_model": false,
    "started_at": "2024-08-18 19:15:18.609511",
    "ended_at": "2024-08-18 19:15:18.744594",
    "duration": "135.083 miliseconds",
    "eval_score": {
        "group_accuracy": "0.4",
        "singleton_f1": "0.67797",
        "ami_score": "0.92422",
        "nmi_score": "0.92915",
        "ari_score": "0.83631",
        "hgi_score": "1.0",
        "cpi_score": "0.86768",
        "vmi_score": "0.92915",
        "fmi_score": "0.87457",
        "silhouette_avg": "0.82493",
        "calinski_harabasz_avg": "4195.75835"
    }
}