{
    "output_dir": "birch-new",
    "dataset": "drone_ovs",
    "embedding": "drone-sbert",
    "threshold": 0.01,
    "save_model": false,
    "started_at": "2024-08-18 01:43:19.254704",
    "ended_at": "2024-08-18 01:43:19.383415",
    "duration": "128.711 miliseconds",
    "eval_score": {
        "group_accuracy": "0.59191",
        "singleton_f1": "0",
        "ami_score": "0.6803",
        "nmi_score": "0.95962",
        "ari_score": "0.66102",
        "hgi_score": "1.0",
        "cpi_score": "0.92237",
        "vmi_score": "0.95962",
        "fmi_score": "0.70315",
        "silhouette_avg": "0.61111",
        "calinski_harabasz_avg": "151486.75963"
    }
}