{
    "output_dir": "birch-new",
    "dataset": "BGL",
    "embedding": "instructor-large",
    "threshold": 0.06,
    "save_model": false,
    "started_at": "2024-08-18 15:46:18.538770",
    "ended_at": "2024-08-18 15:46:18.709199",
    "duration": "170.429 miliseconds",
    "eval_score": {
        "group_accuracy": "0.278",
        "singleton_f1": "0.1303",
        "ami_score": "0.37559",
        "nmi_score": "0.63942",
        "ari_score": "0.0587",
        "hgi_score": "0.99951",
        "cpi_score": "0.47007",
        "vmi_score": "0.63942",
        "fmi_score": "0.1885",
        "silhouette_avg": "0.44964",
        "calinski_harabasz_avg": "184.40253"
    }
}