{
    "output_dir": "birch-new",
    "dataset": "Zookeeper",
    "embedding": "instructor-base",
    "threshold": 0.26,
    "save_model": false,
    "started_at": "2024-08-18 19:31:57.604471",
    "ended_at": "2024-08-18 19:31:57.718909",
    "duration": "114.438 miliseconds",
    "eval_score": {
        "group_accuracy": "0.523",
        "singleton_f1": "0.48",
        "ami_score": "0.92209",
        "nmi_score": "0.92644",
        "ari_score": "0.79847",
        "hgi_score": "0.86417",
        "cpi_score": "0.99837",
        "vmi_score": "0.92644",
        "fmi_score": "0.83725",
        "silhouette_avg": "0.69936",
        "calinski_harabasz_avg": "387.75423"
    }
}